namekox_jsonrpc/__init__.py
namekox_jsonrpc/constants.py
namekox_jsonrpc/exceptions.py
namekox_jsonrpc/cli/__init__.py
namekox_jsonrpc/cli/subctx/__init__.py
namekox_jsonrpc/cli/subctx/jsonrpc.py
namekox_jsonrpc/core/__init__.py
namekox_jsonrpc/core/client.py
namekox_jsonrpc/core/messaging.py
namekox_jsonrpc/core/proxy.py
namekox_jsonrpc/core/entrypoints/__init__.py
namekox_jsonrpc/core/entrypoints/rpc/__init__.py
namekox_jsonrpc/core/entrypoints/rpc/handler.py
namekox_jsonrpc/core/entrypoints/rpc/server.py
namekox_jsonrpc-0.0.11.dist-info/METADATA
namekox_jsonrpc-0.0.11.dist-info/WHEEL
namekox_jsonrpc-0.0.11.dist-info/top_level.txt
namekox_jsonrpc-0.0.11.dist-info/zip-safe
namekox_jsonrpc-0.0.11.dist-info/RECORD
