Metadata-Version: 2.1
Name: namekox-jsonrpc
Version: 0.0.11
Summary: namekox jsonrpc
Home-page: https://forcemain.github.io/
Author: forcemain
License: Apache License, Version 2.0
Platform: UNKNOWN
Classifier: Programming Language :: Python
Classifier: Operating System :: MacOS :: MacOS X
Classifier: Operating System :: POSIX
Classifier: Programming Language :: Python :: 2
Classifier: Programming Language :: Python :: 2.7
Classifier: Programming Language :: Python :: 3
Classifier: Programming Language :: Python :: 3.5
Classifier: Programming Language :: Python :: 3.6
Classifier: Topic :: Internet
Classifier: Topic :: Software Development :: Libraries :: Python Modules
Classifier: Intended Audience :: Developers
Requires-Dist: namekox-webserver
Requires-Dist: anyjson (==0.3.3)
Requires-Dist: urllib3 (<2.0,>=1.8)
